fermion_sandbox/__init__.py
fermion_sandbox/api_client.py
fermion_sandbox/py.typed
fermion_sandbox/sandbox.py
fermion_sandbox/types.py
fermion_sandbox/utils.py
fermion_sandbox/websocket_client.py
fermion_sandbox-0.1.1.dist-info/licenses/LICENSE
fermion_sandbox-0.1.1.dist-info/METADATA
fermion_sandbox-0.1.1.dist-info/WHEEL
fermion_sandbox-0.1.1.dist-info/top_level.txt
fermion_sandbox-0.1.1.dist-info/RECORD
