Metadata-Version: 2.4
Name: fermion-sandbox
Version: 0.1.1
Summary: Secure isolated code execution SDK for Python
Author-email: Fermion <support@fermion.app>
License-Expression: MIT
Project-URL: Homepage, https://docs.fermion.app/
Project-URL: Documentation, https://docs.fermion.app/
Project-URL: Repository, https://github.com/fermion-app/sandbox-python
Project-URL: Issues, https://github.com/fermion-app/sandbox-python/issues
Keywords: code-execution,sandbox,fermion,container,isolation
Classifier: Development Status :: 4 - Beta
Classifier: Intended Audience :: Developers
Classifier: Programming Language :: Python :: 3
Classifier: Programming Language :: Python :: 3.8
Classifier: Programming Language :: Python :: 3.9
Classifier: Programming Language :: Python :: 3.10
Classifier: Programming Language :: Python :: 3.11
Classifier: Programming Language :: Python :: 3.12
Requires-Python: >=3.8
License-File: LICENSE
Requires-Dist: httpx>=0.25.0
Requires-Dist: websockets>=12.0
Requires-Dist: pydantic>=2.0.0
Provides-Extra: dev
Requires-Dist: pytest>=7.4.0; extra == "dev"
Requires-Dist: pytest-asyncio>=0.21.0; extra == "dev"
Requires-Dist: black>=23.0.0; extra == "dev"
Requires-Dist: mypy>=1.5.0; extra == "dev"
Requires-Dist: ruff>=0.1.0; extra == "dev"
Dynamic: license-file
